azure/containerregistry/__init__.py
azure/containerregistry/_anonymous_exchange_client.py
azure/containerregistry/_authentication_policy.py
azure/containerregistry/_base_client.py
azure/containerregistry/_container_registry_client.py
azure/containerregistry/_download_stream.py
azure/containerregistry/_exchange_client.py
azure/containerregistry/_helpers.py
azure/containerregistry/_models.py
azure/containerregistry/_user_agent.py
azure/containerregistry/_version.py
azure/containerregistry/py.typed
azure/containerregistry/_generated/__init__.py
azure/containerregistry/_generated/_client.py
azure/containerregistry/_generated/_configuration.py
azure/containerregistry/_generated/_patch.py
azure/containerregistry/_generated/_serialization.py
azure/containerregistry/_generated/_vendor.py
azure/containerregistry/_generated/aio/__init__.py
azure/containerregistry/_generated/aio/_client.py
azure/containerregistry/_generated/aio/_configuration.py
azure/containerregistry/_generated/aio/_patch.py
azure/containerregistry/_generated/aio/_vendor.py
azure/containerregistry/_generated/aio/operations/__init__.py
azure/containerregistry/_generated/aio/operations/_operations.py
azure/containerregistry/_generated/aio/operations/_patch.py
azure/containerregistry/_generated/models/__init__.py
azure/containerregistry/_generated/models/_enums.py
azure/containerregistry/_generated/models/_models.py
azure/containerregistry/_generated/models/_patch.py
azure/containerregistry/_generated/operations/__init__.py
azure/containerregistry/_generated/operations/_operations.py
azure/containerregistry/_generated/operations/_patch.py
azure/containerregistry/aio/__init__.py
azure/containerregistry/aio/_async_anonymous_exchange_client.py
azure/containerregistry/aio/_async_authentication_policy.py
azure/containerregistry/aio/_async_base_client.py
azure/containerregistry/aio/_async_container_registry_client.py
azure/containerregistry/aio/_async_download_stream.py
azure_containerregistry-1.2.0.dist-info/LICENSE
azure_containerregistry-1.2.0.dist-info/METADATA
azure_containerregistry-1.2.0.dist-info/WHEEL
azure_containerregistry-1.2.0.dist-info/top_level.txt
azure_containerregistry-1.2.0.dist-info/RECORD
